CHANGELOG.txt
LICENCE.txt
MANIFEST.in
README.txt
setup.py
supervised_ml/__init__.py
supervised_ml.egg-info/PKG-INFO
supervised_ml.egg-info/SOURCES.txt
supervised_ml.egg-info/dependency_links.txt
supervised_ml.egg-info/requires.txt
supervised_ml.egg-info/top_level.txt